BetterOdooApiWrapper/__init__.py
BetterOdooApiWrapper/wrapper.py
BetterOdooApiWrapper-0.1.1.dist-info/LICENSE
BetterOdooApiWrapper-0.1.1.dist-info/METADATA
BetterOdooApiWrapper-0.1.1.dist-info/WHEEL
BetterOdooApiWrapper-0.1.1.dist-info/top_level.txt
BetterOdooApiWrapper-0.1.1.dist-info/RECORD
