Metadata-Version: 2.1
Name: BetterOdooApiWrapper
Version: 0.1.1
Summary: A minimal Python ORM wrapper for the Odoo API.
Author-email: Kyan Machiels <kyan.machiels@e-powerinternational.com>, Bert Proesmans <bert.proesmans@e-powerinternational.com>
License: MIT
Project-URL: homepage, https://github.com/europowergenerators/BetterOdooApiWrapper
Project-URL: Documentation, https://github.com/europowergenerators/BetterOdooApiWrapper
Project-URL: Issue tracker, https://github.com/europowergenerators/BetterOdooApiWrapper/issues
Requires-Python: >=3.5
License-File: LICENSE
